yandex_360/__init__.py
yandex_360/_version.py
yandex_360/a2fa.py
yandex_360/antispam.py
yandex_360/auth.py
yandex_360/departments.py
yandex_360/dns.py
yandex_360/domains.py
yandex_360/groups.py
yandex_360/logs.py
yandex_360/mail.py
yandex_360/org.py
yandex_360/pwd.py
yandex_360/routing.py
yandex_360/tools.py
yandex_360/users.py
yandex_360-2.2.1.dist-info/LICENSE
yandex_360-2.2.1.dist-info/METADATA
yandex_360-2.2.1.dist-info/WHEEL
yandex_360-2.2.1.dist-info/top_level.txt
yandex_360-2.2.1.dist-info/RECORD
